gutenfetchen/__init__.py
gutenfetchen/__main__.py
gutenfetchen/api.py
gutenfetchen/boilerplate/license-legacy.txt
gutenfetchen/boilerplate/license-transitional.txt
gutenfetchen/boilerplate/license.txt
gutenfetchen/boilerplate/small-print.txt
gutenfetchen/boilerplate/usage-notice.txt
gutenfetchen/cleaner.py
gutenfetchen/cli.py
gutenfetchen/dedup.py
gutenfetchen/downloader.py
gutenfetchen/models.py
gutenfetchen/naming.py
gutenfetchen-1.2.0.dist-info/METADATA
gutenfetchen-1.2.0.dist-info/WHEEL
gutenfetchen-1.2.0.dist-info/entry_points.txt
gutenfetchen-1.2.0.dist-info/RECORD
