Metadata-Version: 2.1
Name: gutenfetchen
Version: 1.2.0
Summary: Download e-texts from Project Gutenberg
License: MIT
Keywords: gutenberg,ebooks,text,nlp,corpus,download
Author: Craig Trim
Author-email: craigtrim@gmail.com
Requires-Python: >=3.10,<4.0
Classifier: Development Status :: 5 - Production/Stable
Classifier: Intended Audience :: Science/Research
Classifier: License :: OSI Approved :: MIT License
Classifier: Programming Language :: Python :: 3
Classifier: Programming Language :: Python :: 3.10
Classifier: Programming Language :: Python :: 3.11
Classifier: Programming Language :: Python :: 3.12
Classifier: Topic :: Text Processing
Requires-Dist: requests (>=2.31,<3.0)
Requires-Dist: rich (>=13.0,<14.0)
Project-URL: Homepage, https://github.com/craigtrim/gutenfetchen
Project-URL: Repository, https://github.com/craigtrim/gutenfetchen
